README.md
setup.cfg
setup.py
session2s3/__init__.py
session2s3/session2s3.py
session2s3.egg-info/PKG-INFO
session2s3.egg-info/SOURCES.txt
session2s3.egg-info/dependency_links.txt
session2s3.egg-info/requires.txt
session2s3.egg-info/top_level.txt