Metadata-Version: 1.2
Name: session2s3
Version: 0.5a0
Summary: Save your Python session to S3
Home-page: https://github.com/ryninho/session2s3
Author: Eric Rynerson
Author-email: eric.rynerson@gmail.com
License: MIT
Download-URL: https://github.com/ryninho/session2s3/archive/0.5.tar.gz
Keywords: s3,logging,debugging,session,rollback
Platform: UNKNOWN
Classifier: Development Status :: 3 - Alpha
Classifier: Programming Language :: Python :: 2.7
Requires-Python: ==2.7.*
